spe2py.py
spe_loader.py
spe2py-2.0.0.dist-info/DESCRIPTION.rst
spe2py-2.0.0.dist-info/METADATA
spe2py-2.0.0.dist-info/RECORD
spe2py-2.0.0.dist-info/WHEEL
spe2py-2.0.0.dist-info/metadata.json
spe2py-2.0.0.dist-info/top_level.txt
