Metadata-Version: 2.0
Name: spe2py
Version: 2.0.0
Summary: This module imports a Princeton Instruments LightField (SPE 3.0) file into a python environment.
Home-page: https://github.com/ashirsch/spe2py
Author: Alex Hirsch (Zia Lab)
Author-email: alexander_hirsch@brown.edu
License: MIT
Keywords: spectroscopy optics imaging data analysis
Platform: UNKNOWN
Classifier: Development Status :: 5 - Production/Stable
Classifier: Intended Audience :: Science/Research
Classifier: License :: OSI Approved :: MIT License
Classifier: Programming Language :: Python :: 3 :: Only
Requires-Dist: numpy
Requires-Dist: matplotlib
Requires-Dist: untangle
